setup.py
jam65st_probability/BinomialDistribution.py
jam65st_probability/GaussianDistribution.py
jam65st_probability/GeneralDistribution.py
jam65st_probability/__init__.py
jam65st_probability.egg-info/PKG-INFO
jam65st_probability.egg-info/SOURCES.txt
jam65st_probability.egg-info/dependency_links.txt
jam65st_probability.egg-info/not-zip-safe
jam65st_probability.egg-info/top_level.txt