Metadata-Version: 2.1
Name: jam65st-probability
Version: 1.0
Summary: Gaussian distributions
Author: Jaime Mendez
Author-email: jam65st@gmail.com
